orbiteer/__init__.py
orbiteer/inputgenerators/__init__.py
orbiteer/inputgenerators/base.py
orbiteer/inputgenerators/rangegenerator.py
orbiteer/notifiers/__init__.py
orbiteer/optimizers/__init__.py
orbiteer/optimizers/base.py
orbiteer/optimizers/ratio.py
orbiteer/options.py
orbiteer/orbiteer.py
orbiteer/retries/__init__.py
orbiteer/runner.py
orbiteer/targets/__init__.py
orbiteer/targets/base.py
orbiteer/targets/callable.py
orbiteer/targets/command.py
orbiteer-0.2.0.dist-info/LICENSE
orbiteer-0.2.0.dist-info/WHEEL
orbiteer-0.2.0.dist-info/METADATA
orbiteer-0.2.0.dist-info/RECORD
