Metadata-Version: 2.1
Name: orbiteer
Version: 0.2.0
Summary: An optimizing chunking command runner
Home-page: https://github.com/biggerfisch/orbiteer
License: MIT
Author: Avery Fischer
Author-email: avery@averyjfischer.com
Requires-Python: >=3.7,<4.0
Classifier: License :: OSI Approved :: MIT License
Classifier: Programming Language :: Python :: 3
Classifier: Programming Language :: Python :: 3.7
Classifier: Programming Language :: Python :: 3.8
Classifier: Programming Language :: Python :: 3.9
Requires-Dist: typing-extensions (>=4.1.1,<5.0.0)
Project-URL: Repository, https://github.com/biggerfisch/orbiteer
